cron.py
rainydais_cron-1.2.dist-info/LICENSE
rainydais_cron-1.2.dist-info/METADATA
rainydais_cron-1.2.dist-info/WHEEL
rainydais_cron-1.2.dist-info/top_level.txt
rainydais_cron-1.2.dist-info/RECORD
