Metadata-Version: 2.1
Name: rainydais-cron
Version: 1.2
Summary: A lightweight Python library to simplify cron job management.
Author: kgsensei
Author-email: RainyDais <support@rainydais.com>
License: MIT
Project-URL: Homepage, https://rainydais.com
Project-URL: Repository, https://github.com/RainyDais/cron.git
Keywords: cron,cron job,RainyDais,kgsensei
Classifier: Programming Language :: Python
Classifier: Programming Language :: Python :: 3.2
Classifier: Programming Language :: Python :: 3.3
Classifier: Programming Language :: Python :: 3.4
Classifier: Programming Language :: Python :: 3.5
Classifier: Programming Language :: Python :: 3.6
Classifier: Programming Language :: Python :: 3.7
Classifier: Programming Language :: Python :: 3.8
Classifier: Programming Language :: Python :: 3.9
Classifier: Programming Language :: Python :: 3.10
Classifier: Programming Language :: Python :: 3.11
Requires-Python: >=3.2
License-File: LICENSE
